{
  "kind": "collectionType",
  "collectionName": "heroes",
  "info": {
    "singularName": "hero",
    "pluralName": "heroes",
    "displayName": "Hero",
    "description": "Site hero/landing section content"
  },
  "options": {
    "draftAndPublish": true
  },
  "attributes": {
    "title": { "type": "string", "required": true },
    "subtitle": { "type": "string" },
    "background": { "type": "media", "multiple": false, "allowedTypes": ["images"] },
    "mobile_image": { "type": "media", "multiple": false, "allowedTypes": ["images"] },
    "cta_text": { "type": "string" },
    "cta_link": { "type": "string" },
    "order": { "type": "integer" }
  }
}
